balrogo/__init__.py
balrogo/angle.py
balrogo/dynamics.py
balrogo/gaia.py
balrogo/hrd.py
balrogo/marginals.py
balrogo/mock.py
balrogo/parallax.py
balrogo/pm.py
balrogo/position.py
balrogo-1.9.7.dist-info/LICENSE
balrogo-1.9.7.dist-info/METADATA
balrogo-1.9.7.dist-info/WHEEL
balrogo-1.9.7.dist-info/RECORD
