Metadata-Version: 2.1
Name: balrogo
Version: 1.9.7
Summary: Bayesian Astrometric Likelihood Recovery of Galactic Objects
Home-page: https://gitlab.com/eduardo-vitral/balrogo
License: MIT
Author: Eduardo Vitral
Author-email: vitral@iap.fr
Requires-Python: >=3.10,<3.13
Classifier: License :: OSI Approved :: MIT License
Classifier: Programming Language :: Python :: 3
Classifier: Programming Language :: Python :: 3.10
Classifier: Programming Language :: Python :: 3.11
Classifier: Programming Language :: Python :: 3.12
Requires-Dist: astropy (>=5.0,<6.0)
Requires-Dist: emcee (>=3.1.1,<4.0.0)
Requires-Dist: matplotlib (>=3.5.0,<4.0.0)
Requires-Dist: numdifftools (>=0.9.39,<0.10.0)
Requires-Dist: numpy (>=1.21,<2.0)
Requires-Dist: scipy (>=1.8.0,<2.0.0)
Requires-Dist: shapely (>=2,<3)
Project-URL: Repository, https://gitlab.com/eduardo-vitral/balrogo
